pip_manage/__init__.py
pip_manage/_logging.py
pip_manage/_pip_interface.py
pip_manage/pip_purge.py
pip_manage/pip_review.py
pip_manage/py.typed
pip_manage-1.1.2.dist-info/LICENSE
pip_manage-1.1.2.dist-info/METADATA
pip_manage-1.1.2.dist-info/WHEEL
pip_manage-1.1.2.dist-info/entry_points.txt
pip_manage-1.1.2.dist-info/top_level.txt
pip_manage-1.1.2.dist-info/RECORD
